trame/__init__.py
trame/modules/__init__.py
trame/modules/datagrid.py
trame/widgets/__init__.py
trame/widgets/datagrid.py
trame_datagrid/__init__.py
trame_datagrid/module/__init__.py
trame_datagrid/module/datagrid/__init__.py
trame_datagrid/module/datagrid/serve/trame_datagrid.umd.js
trame_datagrid/widgets/__init__.py
trame_datagrid/widgets/datagrid.py
trame_datagrid-0.2.2.dist-info/LICENSE
trame_datagrid-0.2.2.dist-info/METADATA
trame_datagrid-0.2.2.dist-info/WHEEL
trame_datagrid-0.2.2.dist-info/top_level.txt
trame_datagrid-0.2.2.dist-info/RECORD
