Metadata-Version: 2.1
Name: trame-datagrid
Version: 0.2.2
Summary: Trame widget for RevoGrid
Author: Kitware Inc.
License: MIT License
Keywords: Python,Interactive,Web,Application,Framework
Classifier: Development Status :: 4 - Beta
Classifier: Environment :: Web Environment
Classifier: License :: OSI Approved :: MIT License
Classifier: Natural Language :: English
Classifier: Operating System :: OS Independent
Classifier: Programming Language :: Python :: 3 :: Only
Classifier: Programming Language :: JavaScript
Classifier: Topic :: Software Development :: Libraries :: Application Frameworks
Classifier: Topic :: Software Development :: Libraries :: Python Modules
License-File: LICENSE
Requires-Dist: trame-client
